pretty_python/__init__.py
pretty_python/pretty_python.py
pretty_python-0.1.0.dist-info/LICENSE
pretty_python-0.1.0.dist-info/WHEEL
pretty_python-0.1.0.dist-info/METADATA
pretty_python-0.1.0.dist-info/RECORD
